pybubble/__cli__.py
pybubble/__init__.py
pybubble/data.py
pybubble/process.py
pybubble/rootfs.py
pybubble/sandbox.py
pybubble-0.2.0.dist-info/METADATA
pybubble-0.2.0.dist-info/WHEEL
pybubble-0.2.0.dist-info/entry_points.txt
pybubble-0.2.0.dist-info/licenses/LICENSE
pybubble-0.2.0.dist-info/RECORD
