Metadata-Version: 2.4
Name: pybubble
Version: 0.2.0
Summary: A Python package for running sandboxed code.
License-File: LICENSE
Requires-Python: >=3.12
Provides-Extra: test
Requires-Dist: pytest-asyncio>=0.25.2; extra == 'test'
Requires-Dist: pytest>=8.0; extra == 'test'
